takumi/__init__.py
takumi/_compat.py
takumi/exc.py
takumi/log.py
takumi/service.py
takumi/testing.py
takumi/hook/__init__.py
takumi/hook/api.py
takumi-0.1.8.dist-info/DESCRIPTION.rst
takumi-0.1.8.dist-info/METADATA
takumi-0.1.8.dist-info/metadata.json
takumi-0.1.8.dist-info/RECORD
takumi-0.1.8.dist-info/top_level.txt
takumi-0.1.8.dist-info/WHEEL
