Metadata-Version: 2.0
Name: takumi
Version: 0.1.8
Summary: Takumi service framework
Home-page: https://github.com/elemepi/takumi
Author: Eleme Lab
Author-email: imaralla@icloud.com
License: UNKNOWN
Platform: UNKNOWN
Requires-Dist: takumi-config
Requires-Dist: takumi-thrift
Requires-Dist: thriftpy (>=0.3.9)
Requires-Dist: gevent (>=1.2.1)
